h5coro/__init__.py
h5coro/filedriver.py
h5coro/h5coro.py
h5coro/h5dataset.py
h5coro/h5metadata.py
h5coro/h5promise.py
h5coro/h5view.py
h5coro/lazyh5dataset.py
h5coro/logger.py
h5coro/s3driver.py
h5coro/version.py
h5coro/webdriver.py
h5coro/backends/__init__.py
h5coro/backends/xarray_h5coro.py
h5coro/datasets/__init__.py
h5coro/datasets/icesat2.py
h5coro-1.0.4.dist-info/licenses/LICENSE
tests/__init__.py
tests/conftest.py
tests/test_aos.py
tests/test_filedriver.py
tests/test_hdf.py
tests/test_helpers.py
tests/test_icesat2.py
tests/test_multiprocess.py
tests/test_s3driver.py
tests/test_webdriver.py
tests/test_xarray_extension.py
h5coro-1.0.4.dist-info/METADATA
h5coro-1.0.4.dist-info/WHEEL
h5coro-1.0.4.dist-info/entry_points.txt
h5coro-1.0.4.dist-info/top_level.txt
h5coro-1.0.4.dist-info/RECORD
